gadeu/AuthorizationManager.py
gadeu/AuthorizationMethod.py
gadeu/TokenUtil.py
gadeu/__init__.py
gadeu/authorization/__init__.py
gadeu/authorization/apiKey.py
gadeu/authorization/bearerToken.py
gadeu/handlers/ApiKeyAuthorizationHandler.py
gadeu/handlers/AuthorizationHandler.py
gadeu/handlers/BearerTokenAuthorizationHandler.py
gadeu/handlers/__init__.py
gadeu-0.0.9.dist-info/licenses/LICENSE
gadeu-0.0.9.dist-info/METADATA
gadeu-0.0.9.dist-info/WHEEL
gadeu-0.0.9.dist-info/top_level.txt
gadeu-0.0.9.dist-info/RECORD
