Metadata-Version: 2.4
Name: gadeu
Version: 0.0.9
Summary: ..a decorative auth library for Tornado.
Author-email: Shaun Wilson <mrshaunwilson@msn.com>
License-Expression: MIT
Project-URL: Documentation, https://gadeu.readthedocs.io/
Project-URL: Homepage, https://github.com/wilson0x4d/gadeu
Project-URL: Repository, https://github.com/wilson0x4d/gadeu.git
Keywords: tornado,authentication,authorization,apiKey,bearerToken,JWT
Classifier: Operating System :: OS Independent
Classifier: Programming Language :: Python :: 3.12
Classifier: Programming Language :: Python :: 3.13
Classifier: Topic :: Software Development :: Libraries :: Python Modules
Classifier: Intended Audience :: Developers
Requires-Python: >=3.12
License-File: LICENSE
Requires-Dist: base58>=2.1.1
Requires-Dist: cryptography
Requires-Dist: jwcrypto>=1.5.6
Requires-Dist: tornado>=6
Provides-Extra: dev
Requires-Dist: build; extra == "dev"
Requires-Dist: punit>=1.1.4; extra == "dev"
Requires-Dist: twine; extra == "dev"
Requires-Dist: urllib3-future>=2.12.920; extra == "dev"
Dynamic: license-file
